[{
  "_id": {
    "$oid": "6417256de49c73618567e8f2"
  },
  "name": "Ghế 0"
},{
  "_id": {
    "$oid": "6417256de49c73618567e8f3"
  },
  "name": "Ghế 1"
},{
  "_id": {
    "$oid": "6417256de49c73618567e8f4"
  },
  "name": "Ghế 2"
},{
  "_id": {
    "$oid": "6417256de49c73618567e8f5"
  },
  "name": "Ghế 3"
},{
  "_id": {
    "$oid": "6417256de49c73618567e8f6"
  },
  "name": "Ghế 4"
},{
  "_id": {
    "$oid": "6417256de49c73618567e8f7"
  },
  "name": "Ghế 5"
},{
  "_id": {
    "$oid": "6417256de49c73618567e8f8"
  },
  "name": "Ghế 6"
},{
  "_id": {
    "$oid": "6417256de49c73618567e8f9"
  },
  "name": "Ghế 7"
},{
  "_id": {
    "$oid": "6417256de49c73618567e8fa"
  },
  "name": "Ghế 8"
},{
  "_id": {
    "$oid": "6417256de49c73618567e8fb"
  },
  "name": "Ghế 9"
},{
  "_id": {
    "$oid": "6417256de49c73618567e8fc"
  },
  "name": "Ghế 10"
},{
  "_id": {
    "$oid": "6417256de49c73618567e8fd"
  },
  "name": "Ghế 11"
},{
  "_id": {
    "$oid": "6417256de49c73618567e8fe"
  },
  "name": "Ghế 12"
},{
  "_id": {
    "$oid": "6417256de49c73618567e8ff"
  },
  "name": "Ghế 13"
},{
  "_id": {
    "$oid": "6417256de49c73618567e900"
  },
  "name": "Ghế 14"
},{
  "_id": {
    "$oid": "6417256de49c73618567e901"
  },
  "name": "Ghế 15"
},{
  "_id": {
    "$oid": "6417256de49c73618567e902"
  },
  "name": "Ghế 16"
},{
  "_id": {
    "$oid": "6417256de49c73618567e903"
  },
  "name": "Ghế 17"
},{
  "_id": {
    "$oid": "6417256de49c73618567e904"
  },
  "name": "Ghế 18"
},{
  "_id": {
    "$oid": "6417256de49c73618567e905"
  },
  "name": "Ghế 19"
}]